{
	"log" : {

		"systemd" : false,
		"file" : "stdout",
		"level" : "debug"
	},
	"io" : {

		"domain" : {
			"path" : "./src/service/dtn_file_node/config/domain"
		},
		"limits": {
			"reconnect_usecs" : 3000000,
			"timeout_usecs" : 3000000,
			"threadlock_timeout_usec" : 100000
		}
	},
	"dtn" : {

		"routes" : {

			"path" : "./src/service/dtn_file_node/config/routes"
		},

		"node" : {

			"name" : "DTN FILE NODE",
			"path" : "/tmp/opendtn/input",
			"uri"  : "dtn://test/one",

			"socket" : {

				"host" : "127.0.0.1",
				"port" : 14444,
				"type" : "TCP"
			},

			"password" : {
				"blocksize":4,
				"hash":"LjZ5FUfcp9As3IEa4/VZ8KCMOJYY+/8AarZqixgCC5lkp11iHFi4y69IcgsvrM7fsVBOgKLEQMbYaRZM8JpIhA==",
				"parallel":2,
				"salt":"D0NkEp6JMFuXEkYU9hrlfG+DPpnh5y0Qv1LRSeytwl/otArej2IO9HEpLydtfKecuJtjj3qG6Iz+B/RHa+nUlg==",
				"workfactor":1024,
				"NOTE" : "password=admin used for testing, please change"
			},

			"limits" : {

				"threadlock_timeout_usec" : 0,
				"link_check_usec" : 0,
				"message_queue_capacity" : 0,
				"threads" : 0
			},

			"sockets" :
			[
				{
					"host" : "127.0.0.1",
					"type" : "UDP",
					"port" : 4556
				}
			],
			"cbor" :
			{
				"string_size" : 1500,
				"utf8_string_size" : 1500,
				"array_size" : 1000,
				"undef_length_array" : 1000,
				"map_size" : 1000,
				"undef_length_map" : 1000
			}
		}

	}
}